sv_logger_pternali/__init__.py
sv_logger_pternali/sv_logger.py
sv_logger-0.1.6.dist-info/LICENSE
sv_logger-0.1.6.dist-info/METADATA
sv_logger-0.1.6.dist-info/WHEEL
sv_logger-0.1.6.dist-info/top_level.txt
sv_logger-0.1.6.dist-info/RECORD
